adk_slack_adapter/__init__.py
adk_slack_adapter/app_runner.py
adk_slack_adapter/features/__init__.py
adk_slack_adapter/features/interaction_flow.py
adk_slack_adapter/features/slack_event_processor.py
adk_slack_adapter/infrastructure/__init__.py
adk_slack_adapter/infrastructure/adk_adapter.py
adk_slack_adapter/infrastructure/config.py
adk_slack_adapter/infrastructure/slack_adapter.py
adk_slack_adapter-0.2.0.dist-info/METADATA
adk_slack_adapter-0.2.0.dist-info/WHEEL
adk_slack_adapter-0.2.0.dist-info/licenses/LICENSE
adk_slack_adapter-0.2.0.dist-info/RECORD
