Metadata-Version: 2.4
Name: adk-slack-adapter
Version: 0.2.0
Summary: A Python adapter for integrating Google Agent Development Kit (ADK) agents with Slack
Project-URL: Homepage, https://github.com/ktagashira/adk-slack-adapter
Project-URL: Repository, https://github.com/ktagashira/adk-slack-adapter
Project-URL: Issues, https://github.com/ktagashira/adk-slack-adapter/issues
Project-URL: Documentation, https://github.com/ktagashira/adk-slack-adapter#readme
Author-email: Keisuke Tagashira <ktagashira@example.com>
Maintainer-email: Keisuke Tagashira <ktagashira@example.com>
License: MIT
License-File: LICENSE
Keywords: adk,agent,chatbot,google,integration,slack
Classifier: Development Status :: 3 - Alpha
Classifier: Intended Audience :: Developers
Classifier: License :: OSI Approved :: MIT License
Classifier: Operating System :: OS Independent
Classifier: Programming Language :: Python :: 3
Classifier: Programming Language :: Python :: 3.11
Classifier: Programming Language :: Python :: 3.12
Classifier: Topic :: Communications :: Chat
Classifier: Topic :: Software Development :: Libraries :: Python Modules
Requires-Python: >=3.11
Requires-Dist: aiohttp>=3.8.0
Requires-Dist: google-adk>=1.2.1
Requires-Dist: slack-bolt>=1.23.0
Requires-Dist: urllib3>=2.5.0
Provides-Extra: dev
Requires-Dist: black>=23.0.0; extra == 'dev'
Requires-Dist: isort>=5.12.0; extra == 'dev'
Requires-Dist: mypy>=1.0.0; extra == 'dev'
Requires-Dist: pip-audit>=2.6.0; extra == 'dev'
Requires-Dist: pytest-asyncio>=0.21.0; extra == 'dev'
Requires-Dist: pytest-cov>=4.0.0; extra == 'dev'
Requires-Dist: pytest>=7.0.0; extra == 'dev'
Requires-Dist: ruff>=0.1.0; extra == 'dev'
